{
  "workspace": "/home/yanwen/research/agentic/loopmaster/_grasp_runs/capture_anygrasp_grasp_pose-20260711-024008-c303aa",
  "mode": "anygrasp",
  "rgb_path": "/home/yanwen/research/agentic/loopmaster/_grasp_runs/capture_anygrasp_grasp_pose-20260711-024008-c303aa/captures/d435_frame_004357_rgb.png",
  "depth_path": "/home/yanwen/research/agentic/loopmaster/_grasp_runs/capture_anygrasp_grasp_pose-20260711-024008-c303aa/captures/d435_frame_004357_depth.png",
  "debug_image_path": "/home/yanwen/research/agentic/loopmaster/_grasp_runs/capture_anygrasp_grasp_pose-20260711-024008-c303aa/top_grasp_debug.png",
  "extrinsics_path": "/home/yanwen/research/agentic/loopmaster/loopmaster_agentic/config/head_camera_extrinsics.json",
  "camera_to_object": [
    [
      -0.8256055116653442,
      0.42379772663116455,
      -0.37251999974250793,
      0.19380556046962738
    ],
    [
      -0.3314078748226166,
      0.17011751234531403,
      0.9280242323875427,
      0.010115452110767365
    ],
    [
      0.4566667079925537,
      0.8896379470825195,
      -3.888731114898292e-08,
      0.42294764518737793
    ],
    [
      0.0,
      0.0,
      0.0,
      1.0
    ]
  ],
  "right_arm_grasp_pose": [
    [
      0.515340992606876,
      0.29749288622160497,
      -0.8036925800188209,
      0.2327135840949995
    ],
    [
      0.8256055116653442,
      -0.42379772663116455,
      0.37251999974250793,
      0.06619443953037263
    ],
    [
      -0.22978103277285336,
      -0.8555078185167551,
      -0.46401208251637205,
      -0.03134113125846011
    ],
    [
      0.0,
      0.0,
      0.0,
      1.0
    ]
  ],
  "right_arm_target_pose": [
    [
      1.0,
      0.0,
      0.0,
      0.2327135840949995
    ],
    [
      0.0,
      1.0,
      0.0,
      0.06619443953037263
    ],
    [
      0.0,
      0.0,
      1.0,
      0.11865886874153989
    ],
    [
      0.0,
      0.0,
      0.0,
      1.0
    ]
  ],
  "right_arm_target_z_offset_m": 0.15,
  "target_rotation": "fixed",
  "move_arm_ee_args": {
    "side": "right",
    "input_frame": "arm",
    "pose": {
      "position": [
        0.2327135840949995,
        0.06619443953037263,
        0.11865886874153989
      ]
    },
    "execute": true,
    "max_joint_step": 0.05,
    "step_dt": 0.08,
    "hold_s": 0.0,
    "orientation_cost": 0.1,
    "preserve_current_orientation": true,
    "current_positions": {
      "joint_1": -0.1356145590543747,
      "joint_2": -1.3578622341156006,
      "joint_3": -0.91,
      "joint_4": 1.2438009977340698,
      "joint_5": 0.010490577667951584,
      "joint_6": 0.026131074875593185,
      "gripper": -0.21229113638401031
    },
    "other_arm_positions": {
      "joint_1": -0.1356145590543747,
      "joint_2": -1.3578622341156006,
      "joint_3": -0.91,
      "joint_4": 1.2438009977340698,
      "joint_5": 0.010490577667951584,
      "joint_6": 0.026131074875593185,
      "gripper": -0.21229113638401031
    }
  },
  "arm_init_config": "/home/yanwen/research/agentic/loopmaster/loopmaster_agentic/config/arm_init_pose.json",
  "init_arm_positions": {
    "joint_1": -0.1356145590543747,
    "joint_2": -1.3578622341156006,
    "joint_3": -0.91,
    "joint_4": 1.2438009977340698,
    "joint_5": 0.010490577667951584,
    "joint_6": 0.026131074875593185,
    "gripper": -0.21229113638401031
  },
  "init_arm_results": [
    {
      "side": "both",
      "args": {
        "side": "both",
        "positions": {
          "joint_1": -0.1356145590543747,
          "joint_2": -1.3578622341156006,
          "joint_3": -0.91,
          "joint_4": 1.2438009977340698,
          "joint_5": 0.010490577667951584,
          "joint_6": 0.026131074875593185,
          "gripper": -0.21229113638401031
        }
      },
      "result": {
        "ok": true,
        "action_sent": {
          "right_joint_1.pos": -0.1356145590543747,
          "right_joint_2.pos": -1.3578622341156006,
          "right_joint_3.pos": -0.9100000262260437,
          "right_joint_4.pos": 1.2438009977340698,
          "right_joint_5.pos": 0.010490577667951584,
          "right_joint_6.pos": 0.026131074875593185,
          "right_gripper.pos": -0.21229113638401031,
          "left_joint_1.pos": -0.1356145590543747,
          "left_joint_2.pos": -1.3578622341156006,
          "left_joint_3.pos": -0.9100000262260437,
          "left_joint_4.pos": 1.2438009977340698,
          "left_joint_5.pos": 0.010490577667951584,
          "left_joint_6.pos": 0.026131074875593185,
          "left_gripper.pos": -0.21229113638401031,
          "x.vel": 0.0,
          "y.vel": 0.0,
          "theta.vel": 0.0,
          "height.pos": 0.0
        }
      }
    }
  ],
  "move_arm_ee_result": {
    "ok": true,
    "side": "right",
    "executed": true,
    "ik_success": true,
    "positions": {
      "joint_1": 0.25126903664767947,
      "joint_2": -1.575143059408169,
      "joint_3": -1.2394353754697158,
      "joint_4": 1.3502507611272792,
      "joint_5": -0.03732820672044406,
      "joint_6": 0.4095543036239589,
      "gripper": -0.21229113638401031
    },
    "action_sent": {
      "right_joint_1.pos": 0.25126904249191284,
      "right_joint_2.pos": -1.5751430988311768,
      "right_joint_3.pos": -1.2394354343414307,
      "right_joint_4.pos": 1.3502507209777832,
      "right_joint_5.pos": -0.03732820600271225,
      "right_joint_6.pos": 0.40955430269241333,
      "right_gripper.pos": -0.21229113638401031,
      "left_joint_1.pos": -0.1356145590543747,
      "left_joint_2.pos": -1.3578622341156006,
      "left_joint_3.pos": -0.9100000262260437,
      "left_joint_4.pos": 1.2438009977340698,
      "left_joint_5.pos": 0.010490577667951584,
      "left_joint_6.pos": 0.026131074875593185,
      "left_gripper.pos": -0.21229113638401031,
      "x.vel": 0.0,
      "y.vel": 0.0,
      "theta.vel": 0.0,
      "height.pos": 0.0
    },
    "trajectory": [
      {
        "index": 1,
        "steps": 8,
        "positions": {
          "joint_1": -0.08725410959161792,
          "joint_2": -1.3850223372771717,
          "joint_3": -0.9511794219337145,
          "joint_4": 1.257107218158221,
          "joint_5": 0.004513229619402128,
          "joint_6": 0.07405897846913889,
          "gripper": -0.21229113638401031
        },
        "action_sent": {
          "right_joint_1.pos": -0.0872541069984436,
          "right_joint_2.pos": -1.3850222826004028,
          "right_joint_3.pos": -0.9511794447898865,
          "right_joint_4.pos": 1.2571072578430176,
          "right_joint_5.pos": 0.004513229709118605,
          "right_joint_6.pos": 0.07405897974967957,
          "right_gripper.pos": -0.21229113638401031,
          "left_joint_1.pos": -0.1356145590543747,
          "left_joint_2.pos": -1.3578622341156006,
          "left_joint_3.pos": -0.9100000262260437,
          "left_joint_4.pos": 1.2438009977340698,
          "left_joint_5.pos": 0.010490577667951584,
          "left_joint_6.pos": 0.026131074875593185,
          "left_gripper.pos": -0.21229113638401031,
          "x.vel": 0.0,
          "y.vel": 0.0,
          "theta.vel": 0.0,
          "height.pos": 0.0
        }
      },
      {
        "index": 2,
        "steps": 8,
        "positions": {
          "joint_1": -0.038893660128861154,
          "joint_2": -1.4121824404387426,
          "joint_3": -0.992358843867429,
          "joint_4": 1.2704134385823722,
          "joint_5": -0.0014641184291473274,
          "joint_6": 0.12198688206268461,
          "gripper": -0.21229113638401031
        },
        "action_sent": {
          "right_joint_1.pos": -0.03889365866780281,
          "right_joint_2.pos": -1.4121824502944946,
          "right_joint_3.pos": -0.9923588633537292,
          "right_joint_4.pos": 1.2704133987426758,
          "right_joint_5.pos": -0.0014641184825450182,
          "right_joint_6.pos": 0.12198688089847565,
          "right_gripper.pos": -0.21229113638401031,
          "left_joint_1.pos": -0.1356145590543747,
          "left_joint_2.pos": -1.3578622341156006,
          "left_joint_3.pos": -0.9100000262260437,
          "left_joint_4.pos": 1.2438009977340698,
          "left_joint_5.pos": 0.010490577667951584,
          "left_joint_6.pos": 0.026131074875593185,
          "left_gripper.pos": -0.21229113638401031,
          "x.vel": 0.0,
          "y.vel": 0.0,
          "theta.vel": 0.0,
          "height.pos": 0.0
        }
      },
      {
        "index": 3,
        "steps": 8,
        "positions": {
          "joint_1": 0.009466789333895609,
          "joint_2": -1.4393425436003138,
          "joint_3": -1.0335382658011434,
          "joint_4": 1.2837196590065234,
          "joint_5": -0.007441466477696782,
          "joint_6": 0.16991478565623033,
          "gripper": -0.21229113638401031
        },
        "action_sent": {
          "right_joint_1.pos": 0.009466789662837982,
          "right_joint_2.pos": -1.4393424987792969,
          "right_joint_3.pos": -1.0335382223129272,
          "right_joint_4.pos": 1.2837196588516235,
          "right_joint_5.pos": -0.007441466674208641,
          "right_joint_6.pos": 0.16991478204727173,
          "right_gripper.pos": -0.21229113638401031,
          "left_joint_1.pos": -0.1356145590543747,
          "left_joint_2.pos": -1.3578622341156006,
          "left_joint_3.pos": -0.9100000262260437,
          "left_joint_4.pos": 1.2438009977340698,
          "left_joint_5.pos": 0.010490577667951584,
          "left_joint_6.pos": 0.026131074875593185,
          "left_gripper.pos": -0.21229113638401031,
          "x.vel": 0.0,
          "y.vel": 0.0,
          "theta.vel": 0.0,
          "height.pos": 0.0
        }
      },
      {
        "index": 4,
        "steps": 8,
        "positions": {
          "joint_1": 0.057827238796652386,
          "joint_2": -1.4665026467618847,
          "joint_3": -1.0747176877348579,
          "joint_4": 1.2970258794306746,
          "joint_5": -0.013418814526246239,
          "joint_6": 0.21784268924977604,
          "gripper": -0.21229113638401031
        },
        "action_sent": {
          "right_joint_1.pos": 0.057827237993478775,
          "right_joint_2.pos": -1.4665026664733887,
          "right_joint_3.pos": -1.07471764087677,
          "right_joint_4.pos": 1.2970259189605713,
          "right_joint_5.pos": -0.013418814167380333,
          "right_joint_6.pos": 0.2178426831960678,
          "right_gripper.pos": -0.21229113638401031,
          "left_joint_1.pos": -0.1356145590543747,
          "left_joint_2.pos": -1.3578622341156006,
          "left_joint_3.pos": -0.9100000262260437,
          "left_joint_4.pos": 1.2438009977340698,
          "left_joint_5.pos": 0.010490577667951584,
          "left_joint_6.pos": 0.026131074875593185,
          "left_gripper.pos": -0.21229113638401031,
          "x.vel": 0.0,
          "y.vel": 0.0,
          "theta.vel": 0.0,
          "height.pos": 0.0
        }
      },
      {
        "index": 5,
        "steps": 8,
        "positions": {
          "joint_1": 0.10618768825940916,
          "joint_2": -1.4936627499234558,
          "joint_3": -1.1158971096685724,
          "joint_4": 1.3103320998548256,
          "joint_5": -0.019396162574795695,
          "joint_6": 0.2657705928433217,
          "gripper": -0.21229113638401031
        },
        "action_sent": {
          "right_joint_1.pos": 0.10618768632411957,
          "right_joint_2.pos": -1.493662714958191,
          "right_joint_3.pos": -1.1158970594406128,
          "right_joint_4.pos": 1.3103320598602295,
          "right_joint_5.pos": -0.019396161660552025,
          "right_joint_6.pos": 0.2657705843448639,
          "right_gripper.pos": -0.21229113638401031,
          "left_joint_1.pos": -0.1356145590543747,
          "left_joint_2.pos": -1.3578622341156006,
          "left_joint_3.pos": -0.9100000262260437,
          "left_joint_4.pos": 1.2438009977340698,
          "left_joint_5.pos": 0.010490577667951584,
          "left_joint_6.pos": 0.026131074875593185,
          "left_gripper.pos": -0.21229113638401031,
          "x.vel": 0.0,
          "y.vel": 0.0,
          "theta.vel": 0.0,
          "height.pos": 0.0
        }
      },
      {
        "index": 6,
        "steps": 8,
        "positions": {
          "joint_1": 0.1545481377221659,
          "joint_2": -1.520822853085027,
          "joint_3": -1.1570765316022869,
          "joint_4": 1.3236383202789768,
          "joint_5": -0.025373510623345148,
          "joint_6": 0.3136984964368675,
          "gripper": -0.21229113638401031
        },
        "action_sent": {
          "right_joint_1.pos": 0.15454813838005066,
          "right_joint_2.pos": -1.5208228826522827,
          "right_joint_3.pos": -1.1570764780044556,
          "right_joint_4.pos": 1.3236383199691772,
          "right_joint_5.pos": -0.025373511016368866,
          "right_joint_6.pos": 0.31369850039482117,
          "right_gripper.pos": -0.21229113638401031,
          "left_joint_1.pos": -0.1356145590543747,
          "left_joint_2.pos": -1.3578622341156006,
          "left_joint_3.pos": -0.9100000262260437,
          "left_joint_4.pos": 1.2438009977340698,
          "left_joint_5.pos": 0.010490577667951584,
          "left_joint_6.pos": 0.026131074875593185,
          "left_gripper.pos": -0.21229113638401031,
          "x.vel": 0.0,
          "y.vel": 0.0,
          "theta.vel": 0.0,
          "height.pos": 0.0
        }
      },
      {
        "index": 7,
        "steps": 8,
        "positions": {
          "joint_1": 0.20290858718492272,
          "joint_2": -1.5479829562465979,
          "joint_3": -1.1982559535360013,
          "joint_4": 1.336944540703128,
          "joint_5": -0.031350858671894605,
          "joint_6": 0.3616264000304132,
          "gripper": -0.21229113638401031
        },
        "action_sent": {
          "right_joint_1.pos": 0.20290859043598175,
          "right_joint_2.pos": -1.547982931137085,
          "right_joint_3.pos": -1.1982558965682983,
          "right_joint_4.pos": 1.336944580078125,
          "right_joint_5.pos": -0.03135085850954056,
          "right_joint_6.pos": 0.36162638664245605,
          "right_gripper.pos": -0.21229113638401031,
          "left_joint_1.pos": -0.1356145590543747,
          "left_joint_2.pos": -1.3578622341156006,
          "left_joint_3.pos": -0.9100000262260437,
          "left_joint_4.pos": 1.2438009977340698,
          "left_joint_5.pos": 0.010490577667951584,
          "left_joint_6.pos": 0.026131074875593185,
          "left_gripper.pos": -0.21229113638401031,
          "x.vel": 0.0,
          "y.vel": 0.0,
          "theta.vel": 0.0,
          "height.pos": 0.0
        }
      },
      {
        "index": 8,
        "steps": 8,
        "positions": {
          "joint_1": 0.25126903664767947,
          "joint_2": -1.575143059408169,
          "joint_3": -1.2394353754697158,
          "joint_4": 1.3502507611272792,
          "joint_5": -0.03732820672044406,
          "joint_6": 0.4095543036239589,
          "gripper": -0.21229113638401031
        },
        "action_sent": {
          "right_joint_1.pos": 0.25126904249191284,
          "right_joint_2.pos": -1.5751430988311768,
          "right_joint_3.pos": -1.2394354343414307,
          "right_joint_4.pos": 1.3502507209777832,
          "right_joint_5.pos": -0.03732820600271225,
          "right_joint_6.pos": 0.40955430269241333,
          "right_gripper.pos": -0.21229113638401031,
          "left_joint_1.pos": -0.1356145590543747,
          "left_joint_2.pos": -1.3578622341156006,
          "left_joint_3.pos": -0.9100000262260437,
          "left_joint_4.pos": 1.2438009977340698,
          "left_joint_5.pos": 0.010490577667951584,
          "left_joint_6.pos": 0.026131074875593185,
          "left_gripper.pos": -0.21229113638401031,
          "x.vel": 0.0,
          "y.vel": 0.0,
          "theta.vel": 0.0,
          "height.pos": 0.0
        }
      }
    ],
    "target_arm_pose": [
      [
        -0.12087074696958622,
        0.15949780928180554,
        0.979770744287315,
        0.2327135840949995
      ],
      [
        0.005901694449459538,
        0.9871052502695176,
        -0.15996372992956404,
        0.06619443953037263
      ],
      [
        -0.9926507102347933,
        -0.013552627961324268,
        -0.12025345627341633,
        0.11865886874153989
      ],
      [
        0.0,
        0.0,
        0.0,
        1.0
      ]
    ],
    "target_camera_pose": null,
    "transform": null,
    "ik_info": {
      "backend": "mink",
      "solver": "daqp",
      "iterations": 2,
      "position_error_m": 0.007082297648991646,
      "task_position_error_m": 0.007082297787050476,
      "orientation_cost": 0.1,
      "preserve_current_orientation": true,
      "target_world_position": [
        0.2327135840949995,
        -0.16380556046962738,
        0.11865886874153989
      ],
      "reached_world_position": [
        0.22635605260476846,
        -0.16480814497078947,
        0.11570327105957051
      ]
    },
    "orientation_cost": 0.1
  },
  "move_arm_ee_error": null,
  "post_move_arm_positions": {
    "right_joint_1.pos": 0.2309834510087967,
    "right_joint_2.pos": -1.563858985900879,
    "right_joint_3.pos": -1.2220568656921387,
    "right_joint_4.pos": 1.3506141901016235,
    "right_joint_5.pos": -0.03833829239010811,
    "right_joint_6.pos": 0.4079881012439728,
    "right_gripper.pos": -0.212672621011734
  },
  "camera_params": {
    "source": "/home/yanwen/research/agentic/loopmaster/hei-rebot-lift/software/lerobot-hei-rebot-lift/src/lerobot/cameras/d435_intrinsics_640x480.json",
    "fx": 607.03662109375,
    "fy": 606.8038940429688,
    "cx": 316.76116943359375,
    "cy": 242.75991821289062,
    "depth_scale": 999.999952502551,
    "depth_scale_m": 0.0010000000474974513,
    "width": 640,
    "height": 480
  },
  "top_grasp": {
    "index": 0,
    "score": 0.07631813734769821,
    "width": 0.06739968061447144,
    "height": 0.029999999329447746,
    "depth": 0.029999999329447746,
    "translation": [
      0.19380556046962738,
      0.010115452110767365,
      0.42294764518737793
    ],
    "rotation_matrix": [
      [
        -0.8256055116653442,
        0.42379772663116455,
        -0.37251999974250793
      ],
      [
        -0.3314078748226166,
        0.17011751234531403,
        0.9280242323875427
      ],
      [
        0.4566667079925537,
        0.8896379470825195,
        -3.888731114898292e-08
      ]
    ],
    "object_id": -1.0
  },
  "grounded_sam2_result": {
    "ok": true,
    "status": {
      "repo_root": "/home/yanwen/research/agentic/loopmaster/third_party/Grounded-SAM-2",
      "python": "/home/yanwen/research/agentic/loopmaster/.venv/bin/python",
      "dependencies": {
        "cv2": {
          "ok": true,
          "version": "5.0.0"
        },
        "numpy": {
          "ok": true,
          "version": "2.3.5"
        },
        "PIL": {
          "ok": true,
          "version": "12.3.0"
        },
        "torch": {
          "ok": true,
          "version": "2.11.0+cu128"
        },
        "supervision": {
          "ok": true,
          "version": "0.29.1"
        },
        "transformers": {
          "ok": true,
          "version": "5.13.0"
        },
        "pycocotools": {
          "ok": true,
          "version": ""
        }
      }
    },
    "image_path": "/home/yanwen/research/agentic/loopmaster/_grasp_runs/capture_anygrasp_grasp_pose-20260711-024008-c303aa/captures/d435_frame_004357_rgb.png",
    "text_prompt": "yellow bread.",
    "output_dir": "/home/yanwen/research/agentic/loopmaster/_grasp_runs/capture_anygrasp_grasp_pose-20260711-024008-c303aa/grounded_sam2",
    "seg_mask_path": "/home/yanwen/research/agentic/loopmaster/_grasp_runs/capture_anygrasp_grasp_pose-20260711-024008-c303aa/grounded_sam2/seg_mask.png",
    "annotation_count": 1,
    "annotations": [
      {
        "label_id": 1,
        "class_name": "yellow bread",
        "grounding_score": 0.4258439540863037,
        "sam_score": 0.953125,
        "bbox_xyxy": [
          466.78887939453125,
          166.13192749023438,
          609.7988891601562,
          265.1069641113281
        ],
        "mask_path": "/home/yanwen/research/agentic/loopmaster/_grasp_runs/capture_anygrasp_grasp_pose-20260711-024008-c303aa/grounded_sam2/mask_001.png",
        "area_pixels": 9253
      }
    ],
    "anygrasp_hint": {
      "seg_mask_path": "/home/yanwen/research/agentic/loopmaster/_grasp_runs/capture_anygrasp_grasp_pose-20260711-024008-c303aa/grounded_sam2/seg_mask.png",
      "region_object_id": 1
    }
  }
}